cogames_agents/__init__.py
cogames_agents/py.typed
cogames_agents/policy/__init__.py
cogames_agents/policy/cogsguard_roles.py
cogames_agents/policy/cogsguard_teacher.py
cogames_agents/policy/scripted_registry.py
cogames_agents/policy/nim_agents/__init__.py
cogames_agents/policy/nim_agents/agents.py
cogames_agents/policy/nim_agents/cogsguard_agents.nim
cogames_agents/policy/nim_agents/common.nim
cogames_agents/policy/nim_agents/ladybug_agent.nim
cogames_agents/policy/nim_agents/nim_agents.nim
cogames_agents/policy/nim_agents/nim_agents.nims
cogames_agents/policy/nim_agents/nimby.lock
cogames_agents/policy/nim_agents/racecar_agents.nim
cogames_agents/policy/nim_agents/random_agents.nim
cogames_agents/policy/nim_agents/test_agents.py
cogames_agents/policy/nim_agents/thinky_agents.nim
cogames_agents/policy/nim_agents/thinky_eval.py
cogames_agents/policy/nim_agents/bindings/generated/libnim_agents.so
cogames_agents/policy/nim_agents/bindings/generated/nim_agents.py
cogames_agents/policy/scripted_agent/__init__.py
cogames_agents/policy/scripted_agent/baseline_agent.py
cogames_agents/policy/scripted_agent/demo_policy.py
cogames_agents/policy/scripted_agent/pathfinding.py
cogames_agents/policy/scripted_agent/types.py
cogames_agents/policy/scripted_agent/unclipping_agent.py
cogames_agents/policy/scripted_agent/utils.py
cogames_agents/policy/scripted_agent/cogsguard/__init__.py
cogames_agents/policy/scripted_agent/cogsguard/aligner.py
cogames_agents/policy/scripted_agent/cogsguard/debug_agent.py
cogames_agents/policy/scripted_agent/cogsguard/miner.py
cogames_agents/policy/scripted_agent/cogsguard/options.py
cogames_agents/policy/scripted_agent/cogsguard/policy.py
cogames_agents/policy/scripted_agent/cogsguard/scout.py
cogames_agents/policy/scripted_agent/cogsguard/scrambler.py
cogames_agents/policy/scripted_agent/cogsguard/types.py
cogames_agents-0.0.2.dist-info/METADATA
cogames_agents-0.0.2.dist-info/WHEEL
cogames_agents-0.0.2.dist-info/top_level.txt
cogames_agents-0.0.2.dist-info/RECORD
