Metadata-Version: 2.4
Name: cogames-agents
Version: 0.0.2
Summary: Optional agent policies for CoGames
Author: Metta AI
License: MIT
Project-URL: Homepage, https://github.com/Metta-AI/metta/tree/main/packages/cogames-agents
Project-URL: Repository, https://github.com/Metta-AI/metta
Classifier: Programming Language :: Python :: 3
Classifier: Programming Language :: Python :: 3.12
Classifier: License :: OSI Approved :: MIT License
Classifier: Operating System :: POSIX :: Linux
Classifier: Operating System :: MacOS
Requires-Python: <3.13,>=3.12
Requires-Dist: cogames>=0.0.1
Requires-Dist: mettagrid==0.2.0.58
Requires-Dist: numpy>=2.0.0
